django_suc/__init__.py
django_suc/suc.py
django_suc-0.0.4.dist-info/LICENSE
django_suc-0.0.4.dist-info/METADATA
django_suc-0.0.4.dist-info/WHEEL
django_suc-0.0.4.dist-info/top_level.txt
django_suc-0.0.4.dist-info/RECORD
