Metadata-Version: 2.1
Name: django-suc
Version: 0.0.4
Summary: Module for auto-naming unique constraint.
Author-email: Yun Chin <razzzer@gmail.com>
License: BSD 2-Clause License
Classifier: Framework :: Django
Classifier: Programming Language :: Python :: 3
License-File: LICENSE
Requires-Dist: django
